[
  {
    "id": "s0",
    "route": [
      {
        "from": "Padua",
        "to": "Lucca",
        "merchandise": {
          "Apples": 6,
          "Cereal": 42,
          "Detergent": 62,
          "Beef": 9,
          "Tomatoes": 79,
          "Garlic": 92,
          "Spinach": 99,
          "Ketchup": 93,
          "Mustard": 24,
          "Pickles": 57,
          "Paper Towels": 41,
          "Napkins": 38,
          "Tea": 85,
          "Toothbrush": 10,
          "Lotion": 15,
          "Frozen Pizza": 6,
          "Frozen Fruits": 48
        }
      },
      {
        "from": "Lucca",
        "to": "Perugia",
        "merchandise": {
          "Milk": 95,
          "Beer": 88,
          "Coffee": 84,
          "Bananas": 15,
          "Cereal": 59,
          "Toothpaste": 89,
          "Soap": 49,
          "Detergent": 34,
          "Tomatoes": 49,
          "Onions": 8,
          "Potatoes": 25,
          "Chocolate": 96,
          "Tissues": 61,
          "Spinach": 54,
          "Ketchup": 40,
          "Mayonnaise": 26,
          "Pickles": 62,
          "Paper Towels": 84,
          "Napkins": 49,
          "Toothbrush": 6,
          "Lotion": 51,
          "Candles": 63,
          "Frozen Pizza": 79,
          "Frozen Fruits": 48,
          "Frozen Chicken": 31
        }
      },
      {
        "from": "Perugia",
        "to": "Grosseto",
        "merchandise": {
          "Beer": 18,
          "Rice": 83,
          "Apples": 51,
          "Detergent": 50,
          "Beef": 13,
          "Potatoes": 19,
          "Carrots": 11,
          "Pasta": 28,
          "Lettuce": 43,
          "Lotion": 49,
          "Candles": 1
        }
      },
      {
        "from": "Grosseto",
        "to": "Arezzo",
        "merchandise": {
          "Shampoo": 30,
          "Candles": 126,
          "Toilet Paper": 66,
          "Beef": 127,
          "Apples": 83,
          "Eggs": 13,
          "Strudel": 55,
          "Tea": 14,
          "Frozen Vegetables": 83,
          "Onions": 48,
          "Pens": 21,
          "Mayonnaise": 22,
          "Paper Towels": 129,
          "Carrots": 15,
          "Chicken": 137,
          "Lettuce": 91,
          "Cheese": 136,
          "Pepper": 97,
          "Ice Cream": 52,
          "Pasta": 26,
          "Tomatoes": 56,
          "Ketchup": 122,
          "Beer": 68,
          "Tissues": 111,
          "Napkins": 27,
          "Lotion": 26,
          "Avocado": 37
        }
      },
      {
        "from": "Arezzo",
        "to": "Terni",
        "merchandise": {
          "Milk": 87,
          "Beer": 90,
          "Pens": 8,
          "Bread": 43,
          "Coffee": 59,
          "Toothpaste": 69,
          "Shampoo": 98,
          "Cheese": 43,
          "Chicken": 95,
          "Tomatoes": 56,
          "Potatoes": 95,
          "Carrots": 1,
          "Chocolate": 24,
          "Olive Oil": 16,
          "Avocado": 52,
          "Tea": 90,
          "Toothbrush": 34,
          "Lotion": 24,
          "Candles": 2,
          "Frozen Pizza": 48
        }
      },
      {
        "from": "Terni",
        "to": "Latina",
        "merchandise": {
          "Eggs": 61,
          "Coffee": 23,
          "Cereal": 56,
          "Toilet Paper": 97,
          "Cheese": 47,
          "Chicken": 20,
          "Beef": 6,
          "Carrots": 61,
          "Chocolate": 62,
          "Salt": 95,
          "Pepper": 64,
          "Spinach": 46,
          "Ketchup": 44,
          "Mayonnaise": 80,
          "Tea": 73,
          "Lotion": 73,
          "Candles": 22,
          "Frozen Pizza": 49,
          "Frozen Vegetables": 56,
          "Frozen Fruits": 13
        }
      },
      {
        "from": "Latina",
        "to": "Taranto",
        "merchandise": {
          "Apples": 41,
          "Paper Towels": 124,
          "Beef": 138,
          "Tea": 122,
          "Lemons": 92,
          "Mustard": 126,
          "Strudel": 12,
          "Cheese": 138,
          "Soda": 26,
          "Oranges": 22,
          "Garlic": 111,
          "Napkins": 45,
          "Toothpaste": 79,
          "Detergent": 149,
          "Rice": 19,
          "Honey": 110,
          "Potatoes": 90
        }
      }
    ]
  },
  {
    "id": "s1",
    "route": [
      {
        "from": "Torre del Greco",
        "to": "Perugia",
        "merchandise": {
          "Beer": 74,
          "Bananas": 34,
          "Toothpaste": 5,
          "Toilet Paper": 76,
          "Tomatoes": 32,
          "Bottled Water": 77,
          "Chips": 85,
          "Tissues": 84,
          "Olive Oil": 74,
          "Garlic": 73,
          "Mustard": 62,
          "Mayonnaise": 29,
          "Paper Towels": 64,
          "Toothbrush": 95,
          "Lotion": 53,
          "Candles": 2,
          "Strudel": 17,
          "Frozen Pizza": 60,
          "Frozen Chicken": 79
        }
      },
      {
        "from": "Perugia",
        "to": "Turin",
        "merchandise": {
          "Rice": 15,
          "Paper Towels": 46,
          "Sugar": 90,
          "Lettuce": 90,
          "Bread": 119,
          "Spinach": 131,
          "Potatoes": 33,
          "Onions": 30,
          "Oranges": 53,
          "Detergent": 72,
          "Chicken": 103,
          "Apples": 101,
          "Strudel": 69,
          "Ice Cream": 135,
          "Chips": 118,
          "Mustard": 78,
          "Tissues": 149,
          "Pasta": 147,
          "Olive Oil": 108,
          "Tea": 79
        }
      },
      {
        "from": "Turin",
        "to": "Sassari",
        "merchandise": {
          "Eggs": 19,
          "Coffee": 49,
          "Sugar": 42,
          "Shampoo": 36,
          "Cheese": 31,
          "Potatoes": 5,
          "Chocolate": 95,
          "Chips": 48,
          "Pasta": 43,
          "Salt": 76,
          "Spinach": 84,
          "Avocado": 7,
          "Ketchup": 68,
          "Mustard": 4,
          "Paper Towels": 19,
          "Lotion": 68,
          "Strudel": 5
        }
      },
      {
        "from": "Sassari",
        "to": "Terni",
        "merchandise": {
          "Avocado": 102,
          "Beef": 31,
          "Detergent": 72,
          "Bottled Water": 17,
          "Frozen Pizza": 106,
          "Rice": 17,
          "Chips": 134,
          "Soda": 82,
          "Ketchup": 138,
          "Toilet Paper": 24,
          "Toothpaste": 65,
          "Napkins": 137,
          "Mustard": 117,
          "Bananas": 89,
          "Carrots": 34,
          "Beer": 81,
          "Lettuce": 139,
          "Apples": 46,
          "Honey": 30,
          "Pasta": 118,
          "Soap": 79,
          "Cereal": 18,
          "Toothbrush": 123,
          "Mayonnaise": 42,
          "Tissues": 116,
          "Salt": 111,
          "Cheese": 27
        }
      },
      {
        "from": "Terni",
        "to": "Cagliari",
        "merchandise": {
          "Beer": 100,
          "Honey": 92,
          "Bananas": 12,
          "Apples": 15,
          "Oranges": 82,
          "Cereal": 51,
          "Soap": 98,
          "Toilet Paper": 72,
          "Beef": 15,
          "Tomatoes": 70,
          "Potatoes": 92,
          "Tissues": 38,
          "Garlic": 85,
          "Spinach": 41,
          "Ketchup": 37,
          "Mustard": 15,
          "Napkins": 23,
          "Toothbrush": 60,
          "Strudel": 52,
          "Frozen Chicken": 71
        }
      },
      {
        "from": "Cagliari",
        "to": "Sassari",
        "merchandise": {
          "Ketchup": 63,
          "Sugar": 110,
          "Chicken": 24,
          "Frozen Chicken": 63,
          "Shampoo": 131,
          "Beef": 73,
          "Toothpaste": 81,
          "Tea": 90,
          "Toilet Paper": 121,
          "Ice Cream": 67,
          "Mayonnaise": 126,
          "Pepper": 145,
          "Bread": 107
        }
      },
      {
        "from": "Sassari",
        "to": "Cesena",
        "merchandise": {
          "Beer": 3,
          "Pens": 31,
          "Eggs": 90,
          "Rice": 49,
          "Bananas": 40,
          "Apples": 42,
          "Toothpaste": 15,
          "Shampoo": 6,
          "Onions": 76,
          "Bottled Water": 33,
          "Chips": 16,
          "Olive Oil": 63,
          "Salt": 41,
          "Pepper": 77,
          "Garlic": 2,
          "Lemons": 76,
          "Mayonnaise": 36,
          "Paper Towels": 9,
          "Napkins": 83,
          "Candles": 1,
          "Ice Cream": 89,
          "Frozen Pizza": 54
        }
      }
    ]
  },
  {
    "id": "s2",
    "route": [
      {
        "from": "Catanzaro",
        "to": "Pozzuoli",
        "merchandise": {
          "Chicken": 67,
          "Lotion": 103,
          "Beef": 89,
          "Salt": 74,
          "Paper Towels": 50,
          "Cheese": 89,
          "Pens": 79,
          "Bananas": 115,
          "Garlic": 77,
          "Strudel": 128,
          "Oranges": 68,
          "Rice": 30,
          "Honey": 11,
          "Frozen Fruits": 73,
          "Toothbrush": 63,
          "Chocolate": 141,
          "Mustard": 61,
          "Bottled Water": 66,
          "Toothpaste": 106,
          "Napkins": 90,
          "Lemons": 27,
          "Ice Cream": 32,
          "Beer": 104,
          "Detergent": 121,
          "Tea": 30,
          "Tomatoes": 53,
          "Candles": 137
        }
      },
      {
        "from": "Pozzuoli",
        "to": "Turin",
        "merchandise": {
          "Apples": 18,
          "Pickles": 34,
          "Sugar": 81,
          "Spinach": 140,
          "Cereal": 146,
          "Napkins": 89,
          "Toothbrush": 34,
          "Lemons": 57,
          "Ice Cream": 127,
          "Chocolate": 81,
          "Potatoes": 73,
          "Eggs": 22,
          "Coffee": 26,
          "Frozen Pizza": 55,
          "Rice": 139
        }
      },
      {
        "from": "Turin",
        "to": "Ravenna",
        "merchandise": {
          "Beef": 97,
          "Rice": 117,
          "Olive Oil": 101,
          "Lotion": 117,
          "Chips": 19,
          "Lettuce": 117,
          "Potatoes": 65,
          "Pickles": 124,
          "Pepper": 12,
          "Soap": 126,
          "Carrots": 121,
          "Shampoo": 145,
          "Bread": 46,
          "Lemons": 130,
          "Mayonnaise": 13,
          "Beer": 13,
          "Frozen Pizza": 64,
          "Garlic": 77,
          "Pens": 103,
          "Honey": 146,
          "Sugar": 53,
          "Milk": 111,
          "Oranges": 35,
          "Ketchup": 38,
          "Soda": 38,
          "Frozen Fruits": 134,
          "Apples": 150,
          "Pasta": 81,
          "Toothpaste": 104,
          "Cereal": 74
        }
      },
      {
        "from": "Ravenna",
        "to": "Reggio Calabria",
        "merchandise": {
          "Milk": 73,
          "Pens": 94,
          "Detergent": 50,
          "Tomatoes": 95,
          "Soda": 36,
          "Tissues": 11,
          "Garlic": 25,
          "Spinach": 52,
          "Avocado": 33,
          "Mayonnaise": 24,
          "Pickles": 47,
          "Napkins": 22,
          "Candles": 23
        }
      },
      {
        "from": "Reggio Calabria",
        "to": "Pesaro",
        "merchandise": {
          "Toothpaste": 85,
          "Toilet Paper": 40,
          "Tomatoes": 85,
          "Onions": 22,
          "Carrots": 24,
          "Soda": 91,
          "Pasta": 84,
          "Salt": 54,
          "Pepper": 82,
          "Spinach": 92,
          "Avocado": 22,
          "Mustard": 23,
          "Mayonnaise": 72,
          "Paper Towels": 32,
          "Napkins": 20,
          "Toothbrush": 33,
          "Strudel": 9,
          "Frozen Fruits": 45
        }
      },
      {
        "from": "Pesaro",
        "to": "Taranto",
        "merchandise": {
          "Milk": 76,
          "Honey": 27,
          "Bread": 73,
          "Bananas": 18,
          "Cereal": 76,
          "Toothpaste": 36,
          "Toilet Paper": 45,
          "Beef": 1,
          "Carrots": 84,
          "Bottled Water": 83,
          "Soda": 10,
          "Pasta": 85,
          "Olive Oil": 19,
          "Lettuce": 74,
          "Avocado": 1,
          "Paper Towels": 12,
          "Tea": 90,
          "Frozen Vegetables": 26
        }
      },
      {
        "from": "Taranto",
        "to": "Bari",
        "merchandise": {
          "Milk": 44,
          "Bread": 40,
          "Rice": 29,
          "Cereal": 44,
          "Chicken": 95,
          "Onions": 44,
          "Soda": 65,
          "Olive Oil": 61,
          "Salt": 11,
          "Garlic": 87,
          "Lemons": 88,
          "Mayonnaise": 60,
          "Lotion": 16,
          "Candles": 70,
          "Ice Cream": 71
        }
      },
      {
        "from": "Bari",
        "to": "Reggio Calabria",
        "merchandise": {
          "Honey": 63,
          "Bread": 29,
          "Bananas": 85,
          "Oranges": 98,
          "Cereal": 90,
          "Toilet Paper": 34,
          "Chicken": 10,
          "Beef": 90,
          "Tomatoes": 35,
          "Chocolate": 13,
          "Chips": 100,
          "Olive Oil": 24,
          "Salt": 23,
          "Pepper": 7,
          "Garlic": 4,
          "Spinach": 4,
          "Lemons": 16,
          "Mayonnaise": 5,
          "Pickles": 89
        }
      }
    ]
  },
  {
    "id": "s3",
    "route": [
      {
        "from": "Cesena",
        "to": "Forli",
        "merchandise": {
          "Beer": 125,
          "Apples": 56,
          "Paper Towels": 147,
          "Chocolate": 122,
          "Tissues": 37,
          "Frozen Fruits": 84,
          "Avocado": 51,
          "Bottled Water": 27,
          "Sugar": 139,
          "Detergent": 115,
          "Toilet Paper": 77,
          "Pens": 141,
          "Chicken": 33,
          "Pasta": 15,
          "Bread": 128,
          "Frozen Pizza": 42
        }
      },
      {
        "from": "Forli",
        "to": "Mestre",
        "merchandise": {
          "Beer": 92,
          "Sugar": 8,
          "Oranges": 36,
          "Cereal": 27,
          "Shampoo": 67,
          "Soap": 27,
          "Cheese": 55,
          "Chicken": 68,
          "Tomatoes": 27,
          "Onions": 97,
          "Bottled Water": 50,
          "Tissues": 40,
          "Olive Oil": 99,
          "Spinach": 48,
          "Lemons": 15,
          "Pickles": 69,
          "Napkins": 22,
          "Lotion": 37,
          "Candles": 79
        }
      },
      {
        "from": "Mestre",
        "to": "Bologna",
        "merchandise": {
          "Beer": 3,
          "Pens": 38,
          "Bread": 90,
          "Eggs": 84,
          "Coffee": 74,
          "Rice": 86,
          "Oranges": 83,
          "Shampoo": 73,
          "Toilet Paper": 30,
          "Tomatoes": 71,
          "Carrots": 77,
          "Bottled Water": 80,
          "Chips": 17,
          "Pasta": 19,
          "Salt": 6,
          "Pepper": 58,
          "Lettuce": 60,
          "Spinach": 15,
          "Avocado": 77,
          "Mustard": 82,
          "Mayonnaise": 67,
          "Tea": 63,
          "Candles": 52,
          "Frozen Pizza": 23
        }
      },
      {
        "from": "Bologna",
        "to": "Reggio Calabria",
        "merchandise": {
          "Chips": 62,
          "Garlic": 103,
          "Lotion": 134,
          "Frozen Fruits": 35,
          "Coffee": 124,
          "Cereal": 129,
          "Toilet Paper": 79,
          "Beef": 20,
          "Chicken": 26,
          "Tea": 100,
          "Sugar": 38,
          "Mayonnaise": 27,
          "Bottled Water": 58,
          "Pickles": 114,
          "Mustard": 132,
          "Pens": 94,
          "Chocolate": 137,
          "Oranges": 81,
          "Ketchup": 119,
          "Salt": 67,
          "Avocado": 118,
          "Lemons": 66,
          "Strudel": 10,
          "Paper Towels": 32,
          "Pasta": 125,
          "Olive Oil": 92
        }
      },
      {
        "from": "Reggio Calabria",
        "to": "Salerno",
        "merchandise": {
          "Eggs": 98,
          "Coffee": 34,
          "Bananas": 7,
          "Oranges": 31,
          "Shampoo": 25,
          "Soap": 60,
          "Detergent": 13,
          "Cheese": 94,
          "Onions": 94,
          "Bottled Water": 83,
          "Pepper": 8,
          "Mustard": 23,
          "Paper Towels": 43,
          "Tea": 18,
          "Toothbrush": 68,
          "Frozen Pizza": 60,
          "Frozen Fruits": 33
        }
      },
      {
        "from": "Salerno",
        "to": "Fiumicino",
        "merchandise": {
          "Frozen Pizza": 121,
          "Pasta": 39,
          "Onions": 59,
          "Salt": 136,
          "Carrots": 127,
          "Toothpaste": 53,
          "Ice Cream": 10,
          "Mustard": 142,
          "Coffee": 33,
          "Candles": 136,
          "Detergent": 69,
          "Beer": 85,
          "Apples": 54,
          "Beef": 95,
          "Chips": 138,
          "Soda": 126,
          "Rice": 77,
          "Frozen Fruits": 84,
          "Paper Towels": 44,
          "Oranges": 28,
          "Soap": 108
        }
      }
    ]
  }
]